MusiCore/__init__.py
MusiCore/Player/Player.py
MusiCore/Player/Sound.py
MusiCore/Playlist/Path.py
MusiCore/Playlist/_Playlist.py
MusiCore/Stream/Stream.py
MusiCore_Oui002-0.0.6.3.9.dist-info/LICENSE
MusiCore_Oui002-0.0.6.3.9.dist-info/METADATA
MusiCore_Oui002-0.0.6.3.9.dist-info/WHEEL
MusiCore_Oui002-0.0.6.3.9.dist-info/top_level.txt
MusiCore_Oui002-0.0.6.3.9.dist-info/RECORD
