Metadata-Version: 2.1
Name: MusiCore-Oui002
Version: 0.0.6.3.9
Summary: Module for playing wave files in buffers. Also has a basic music player functions like playlists and stuff like that :)) 
Home-page: https://github.com/Oui002/MusiCore
Author: https://github.com/Oui002
License: UNKNOWN
Platform: UNKNOWN
Classifier: Programming Language :: Python :: 3
Classifier: License :: OSI Approved :: MIT License
Requires-Python: >=3.6
License-File: LICENSE
